dvk_archive/__init__.py
dvk_archive/main/__init__.py
dvk_archive/main/color_print.py
dvk_archive/main/error_finding/__init__.py
dvk_archive/main/error_finding/missing_media.py
dvk_archive/main/error_finding/missing_sequence_info.py
dvk_archive/main/error_finding/same_ids.py
dvk_archive/main/error_finding/sequence_errors.py
dvk_archive/main/error_finding/unlinked_media.py
dvk_archive/main/file/__init__.py
dvk_archive/main/file/dvk.py
dvk_archive/main/file/dvk_handler.py
dvk_archive/main/file/dvk_html.py
dvk_archive/main/file/manual_dvk.py
dvk_archive/main/file/reformat.py
dvk_archive/main/file/rename.py
dvk_archive/main/file/sequencing.py
dvk_archive/main/processing/__init__.py
dvk_archive/main/processing/html_processing.py
dvk_archive/main/processing/list_processing.py
dvk_archive/main/processing/string_compare.py
dvk_archive/main/processing/string_processing.py
dvk_archive/main/web/__init__.py
dvk_archive/main/web/bs_connect.py
dvk_archive/main/web/heavy_connect.py
dvk_archive/test/__init__.py
dvk_archive/test/all_tests.py
dvk_archive/test/temp_dir.py
dvk_archive/test/error_finding/__init__.py
dvk_archive/test/error_finding/error_files.py
dvk_archive/test/error_finding/error_finding_tests.py
dvk_archive/test/error_finding/test_missing_media.py
dvk_archive/test/error_finding/test_missing_sequence_info.py
dvk_archive/test/error_finding/test_same_ids.py
dvk_archive/test/error_finding/test_sequence_errors.py
dvk_archive/test/error_finding/test_unlinked_media.py
dvk_archive/test/file/__init__.py
dvk_archive/test/file/file_tests.py
dvk_archive/test/file/test_dvk.py
dvk_archive/test/file/test_dvk_handler.py
dvk_archive/test/file/test_dvk_html.py
dvk_archive/test/file/test_manual_dvk.py
dvk_archive/test/file/test_reformat.py
dvk_archive/test/file/test_rename.py
dvk_archive/test/file/test_sequencing.py
dvk_archive/test/processing/__init__.py
dvk_archive/test/processing/processing_tests.py
dvk_archive/test/processing/test_html_processing.py
dvk_archive-0.13.2.dist-info/LICENSE
dvk_archive-0.13.2.dist-info/METADATA
dvk_archive-0.13.2.dist-info/WHEEL
dvk_archive-0.13.2.dist-info/entry_points.txt
dvk_archive-0.13.2.dist-info/top_level.txt
dvk_archive-0.13.2.dist-info/RECORD
