Metadata-Version: 2.1
Name: dvk-archive
Version: 0.13.2
Summary: Utility for loading and handling media files in the DVK file format.
Home-page: https://github.com/Drakovek/dvk_archive
Author: Drakovek
Author-email: DrakovekMail@gmail.com
Classifier: Programming Language :: Python :: 3
Classifier: License :: OSI Approved :: GNU General Public License v3 (GPLv3)
Classifier: Operating System :: OS Independent
Requires-Python: >=3.0
License-File: LICENSE
Requires-Dist: beautifulsoup4
Requires-Dist: filetype
Requires-Dist: html5lib
Requires-Dist: HTML-String-Tools
Requires-Dist: lxml
Requires-Dist: requests
Requires-Dist: selenium
Requires-Dist: tqdm
